ckanext/__init__.py
ckanext/status/__init__.py
ckanext/status/interfaces.py
ckanext/status/plugin.py
ckanext/status/lib/__init__.py
ckanext/status/lib/helpers.py
ckanext/status/lib/utils.py
ckanext/status/logic/__init__.py
ckanext/status/logic/actions.py
ckanext/status/logic/auth.py
ckanext/status/routes/__init__.py
ckanext/status/routes/status.py
ckanext/status/theme/assets/webassets.yml
ckanext/status/theme/assets/less/status.less
ckanext/status/theme/templates/page.html
ckanext/status/theme/templates/admin/config.html
ckanext/status/theme/templates/status/index.html
ckanext_status-2.4.4.dist-info/licenses/LICENSE
docs/_scripts/gen_api_pages.py
ckanext_status-2.4.4.dist-info/METADATA
ckanext_status-2.4.4.dist-info/WHEEL
ckanext_status-2.4.4.dist-info/entry_points.txt
ckanext_status-2.4.4.dist-info/top_level.txt
ckanext_status-2.4.4.dist-info/RECORD
